package pkg;

super public class TestConstructorThisCallAfterBranch
  version 47:0
{

private Field name:"Ljava/lang/String;";
private Field value:"Ljava/lang/Object;";

private Method "<init>":"(Ljava/lang/String;Ljava/lang/Object;)V"
  stack 2 locals 3
{
  aload_0;
  invokespecial Method java/lang/Object."<init>":"()V";
  aload_0;
  aload_1;
  putfield Field name:"Ljava/lang/String;";
  aload_0;
  aload_2;
  putfield Field value:"Ljava/lang/Object;";
  return;
}

public Method "<init>":"(Ljava/lang/String;)V"
  stack 3 locals 3
{
  aload_1;
  ldc String "buffer";
  invokevirtual Method java/lang/String.equals:"(Ljava/lang/Object;)Z";
  ifeq LString;
  new class java/lang/StringBuffer;
  dup;
  ldc String "chosen";
  invokespecial Method java/lang/StringBuffer."<init>":"(Ljava/lang/String;)V";
  astore_2;
  goto LCall;
LString:
  ldc String "chosen";
  astore_2;
LCall:
  aload_0;
  aload_1;
  aload_2;
  invokespecial Method "<init>":"(Ljava/lang/String;Ljava/lang/Object;)V";
  return;
}

} // end Class TestConstructorThisCallAfterBranch
