package pkg;

super public class TestConstructorPreinitLookupThis
  version 47:0
{

private Field input:"Lpkg/TestConstructorPreinitLookupInput;";
private Field size:"I";
private static Field sizes:"Ljava/util/Hashtable;";

public Method "<init>":"(Lpkg/TestConstructorPreinitLookupInput;)V"
  stack 4 locals 4
{
  aload_1;
  astore_1;
  aload_1;
  instanceof class pkg/TestConstructorPreinitLookupSpecial;
  ifeq LLookup;
  bipush 64;
  istore_3;
  goto LCall;
LLookup:
  getstatic Field sizes:"Ljava/util/Hashtable;";
  aload_1;
  invokevirtual Method pkg/TestConstructorPreinitLookupInput.name:"()Ljava/lang/String;";
  invokevirtual Method java/util/Hashtable.get:"(Ljava/lang/Object;)Ljava/lang/Object;";
  checkcast class java/lang/Integer;
  astore_2;
  aload_2;
  ifnonnull LFound;
  new class java/lang/IllegalArgumentException;
  dup;
  ldc String "unknown";
  invokespecial Method java/lang/IllegalArgumentException."<init>":"(Ljava/lang/String;)V";
  athrow;
LFound:
  aload_2;
  invokevirtual Method java/lang/Integer.intValue:"()I";
  istore_3;
LCall:
  aload_0;
  aload_1;
  iload_3;
  invokespecial Method "<init>":"(Lpkg/TestConstructorPreinitLookupInput;I)V";
  return;
}

private Method "<init>":"(Lpkg/TestConstructorPreinitLookupInput;I)V"
  stack 2 locals 3
{
  aload_0;
  invokespecial Method java/lang/Object."<init>":"()V";
  aload_0;
  aload_1;
  putfield Field input:"Lpkg/TestConstructorPreinitLookupInput;";
  aload_0;
  iload_2;
  putfield Field size:"I";
  return;
}

static Method "<clinit>":"()V"
  stack 5 locals 0
{
  new class java/util/Hashtable;
  dup;
  invokespecial Method java/util/Hashtable."<init>":"()V";
  putstatic Field sizes:"Ljava/util/Hashtable;";
  getstatic Field sizes:"Ljava/util/Hashtable;";
  ldc String "MD5";
  new class java/lang/Integer;
  dup;
  bipush 64;
  invokespecial Method java/lang/Integer."<init>":"(I)V";
  invokevirtual Method java/util/Hashtable.put:"(Ljava/lang/Object;Ljava/lang/Object;)Ljava/lang/Object;";
  pop;
  return;
}

} // end Class TestConstructorPreinitLookupThis
