package pkg;

super public class TestStaticInitializerTryFinallyBreak
  version 49:0
{

public static Field flags:"[B";
public static Field data:"[[B";

public Method "<init>":"()V"
  stack 1 locals 1
{
  aload_0;
  invokespecial Method java/lang/Object."<init>":"()V";
  return;
}

private static Method open:"()Ljava/io/InputStream;"
  stack 4 locals 0
{
  new class java/io/ByteArrayInputStream;
  dup;
  iconst_3;
  newarray byte;
  dup;
  iconst_0;
  iconst_1;
  bastore;
  invokespecial Method java/io/ByteArrayInputStream."<init>":"([B)V";
  areturn;
}

static Method "<clinit>":"()V"
  stack 4 locals 2
{
  bipush 10;
  newarray byte;
  putstatic Field flags:"[B";
  bipush 10;
  anewarray class "[B";
  putstatic Field data:"[[B";
  invokestatic Method open:"()Ljava/io/InputStream;";
  astore_0;
  try t_body;
    aload_0;
    invokevirtual Method java/io/InputStream.read:"()I";
    pop;
    iconst_0;
    istore_1;
  LLoop:
    iload_1;
    bipush 10;
    if_icmpge LBreak;
    getstatic Field data:"[[B";
    iload_1;
    aload_0;
    invokevirtual Method java/io/InputStream.read:"()I";
    newarray byte;
    aastore;
    aload_0;
    getstatic Field data:"[[B";
    iload_1;
    aaload;
    invokevirtual Method java/io/InputStream.read:"([B)I";
    pop;
    getstatic Field flags:"[B";
    iload_1;
    bipush 9;
    bastore;
    iinc 1, 1;
    goto LLoop;
  LBreak:
  endtry t_body;
  try t_close_normal;
    aload_0;
    ifnull LReturn;
    aload_0;
    invokevirtual Method java/io/InputStream.close:"()V";
  LReturn:
    return;
  endtry t_close_normal;
  catch t_close_normal java/io/IOException;
    stack_frame_type stack1;
    stack_map class java/io/IOException;
    dup;
    astore_1;
    invokevirtual Method java/io/IOException.printStackTrace:"()V";
    return;
  catch t_body java/lang/Exception;
    stack_frame_type stack1;
    stack_map class java/lang/Exception;
    dup;
    astore_1;
    invokevirtual Method java/lang/Exception.printStackTrace:"()V";
  try t_close_catch;
    aload_0;
    ifnull LCatchReturn;
    aload_0;
    invokevirtual Method java/io/InputStream.close:"()V";
  LCatchReturn:
    return;
  endtry t_close_catch;
  catch t_close_catch java/io/IOException;
    stack_frame_type stack1;
    stack_map class java/io/IOException;
    dup;
    astore_1;
    invokevirtual Method java/io/IOException.printStackTrace:"()V";
    return;
  catch t_body null;
    stack_frame_type stack1;
    stack_map class java/lang/Throwable;
    astore_1;
  try t_close_any;
    aload_0;
    ifnull LThrow;
    aload_0;
    invokevirtual Method java/io/InputStream.close:"()V";
  LThrow:
    goto LAfterCloseAny;
  endtry t_close_any;
  catch t_close_any java/io/IOException;
    stack_frame_type stack1;
    stack_map class java/io/IOException;
    dup;
    astore_0;
    invokevirtual Method java/io/IOException.printStackTrace:"()V";
  LAfterCloseAny:
    aload_1;
    athrow;
}

} // end Class TestStaticInitializerTryFinallyBreak
