package pkg;

super public class TestConstructorPreinitMutatingSuperArg extends pkg/TestConstructorPreinitHashtableBase
  version 47:0
{

public Method "<init>":"(Ljava/util/Hashtable;)V"
  stack 4 locals 3
{
  aload_1;
  astore_2;
  aload_2;
  ldc String "pid";
  aload_2;
  ldc String "gid";
  invokevirtual Method java/util/Hashtable.get:"(Ljava/lang/Object;)Ljava/lang/Object;";
  invokevirtual Method java/util/Hashtable.put:"(Ljava/lang/Object;Ljava/lang/Object;)Ljava/lang/Object;";
  pop;
  aload_2;
  ldc String "gid";
  invokevirtual Method java/util/Hashtable.remove:"(Ljava/lang/Object;)Ljava/lang/Object;";
  pop;
  aload_0;
  aload_2;
  invokespecial Method pkg/TestConstructorPreinitHashtableBase."<init>":"(Ljava/util/Hashtable;)V";
  return;
}

} // end Class TestConstructorPreinitMutatingSuperArg
